{
   "results" : [
      {
         "address_components" : [
            {
               "long_name" : "3228",
               "short_name" : "3228",
               "types" : [ "street_number" ]
            },
            {
               "long_name" : "Clemenceau Boulevard",
               "short_name" : "Clemenceau Blvd",
               "types" : [ "route" ]
            },
            {
               "long_name" : "Forest Glade",
               "short_name" : "Forest Glade",
               "types" : [ "neighborhood", "political" ]
            },
            {
               "long_name" : "Windsor",
               "short_name" : "Windsor",
               "types" : [ "locality", "political" ]
            },
            {
               "long_name" : "Essex County",
               "short_name" : "Essex County",
               "types" : [ "administrative_area_level_2", "political" ]
            },
            {
               "long_name" : "Ontario",
               "short_name" : "ON",
               "types" : [ "administrative_area_level_1", "political" ]
            },
            {
               "long_name" : "Canada",
               "short_name" : "CA",
               "types" : [ "country", "political" ]
            },
            {
               "long_name" : "N8T 2R7",
               "short_name" : "N8T 2R7",
               "types" : [ "postal_code" ]
            }
         ],
         "formatted_address" : "3228 Clemenceau Blvd, Windsor, ON N8T 2R7, Canada",
         "geometry" : {
            "bounds" : {
               "northeast" : {
                  "lat" : 42.2924662,
                  "lng" : -82.943433
               },
               "southwest" : {
                  "lat" : 42.29246029999999,
                  "lng" : -82.94345
               }
            },
            "location" : {
               "lat" : 42.29246029999999,
               "lng" : -82.94345
            },
            "location_type" : "RANGE_INTERPOLATED",
            "viewport" : {
               "northeast" : {
                  "lat" : 42.29381223029149,
                  "lng" : -82.9420925197085
               },
               "southwest" : {
                  "lat" : 42.2911142697085,
                  "lng" : -82.9447904802915
               }
            }
         },
         "partial_match" : true,
         "place_id" : "EjEzMjI4IENsZW1lbmNlYXUgQmx2ZCwgV2luZHNvciwgT04gTjhUIDJSNywgQ2FuYWRh",
         "types" : [ "street_address" ]
      }
   ],
   "status" : "OK"
}
