{
   "results" : [
      {
         "address_components" : [
            {
               "long_name" : "782",
               "short_name" : "782",
               "types" : [ "street_number" ]
            },
            {
               "long_name" : "Bridge Avenue",
               "short_name" : "Bridge Ave",
               "types" : [ "route" ]
            },
            {
               "long_name" : "University",
               "short_name" : "University",
               "types" : [ "neighborhood", "political" ]
            },
            {
               "long_name" : "Windsor",
               "short_name" : "Windsor",
               "types" : [ "locality", "political" ]
            },
            {
               "long_name" : "Essex County",
               "short_name" : "Essex County",
               "types" : [ "administrative_area_level_2", "political" ]
            },
            {
               "long_name" : "Ontario",
               "short_name" : "ON",
               "types" : [ "administrative_area_level_1", "political" ]
            },
            {
               "long_name" : "Canada",
               "short_name" : "CA",
               "types" : [ "country", "political" ]
            },
            {
               "long_name" : "N9B 2M6",
               "short_name" : "N9B 2M6",
               "types" : [ "postal_code" ]
            }
         ],
         "formatted_address" : "782 Bridge Ave, Windsor, ON N9B 2M6, Canada",
         "geometry" : {
            "bounds" : {
               "northeast" : {
                  "lat" : 42.304494,
                  "lng" : -83.0566225
               },
               "southwest" : {
                  "lat" : 42.3044881,
                  "lng" : -83.0566395
               }
            },
            "location" : {
               "lat" : 42.3044881,
               "lng" : -83.0566395
            },
            "location_type" : "RANGE_INTERPOLATED",
            "viewport" : {
               "northeast" : {
                  "lat" : 42.3058400302915,
                  "lng" : -83.0552820197085
               },
               "southwest" : {
                  "lat" : 42.3031420697085,
                  "lng" : -83.05797998029152
               }
            }
         },
         "partial_match" : true,
         "place_id" : "Eis3ODIgQnJpZGdlIEF2ZSwgV2luZHNvciwgT04gTjlCIDJNNiwgQ2FuYWRh",
         "types" : [ "street_address" ]
      }
   ],
   "status" : "OK"
}
