{
   "results" : [
      {
         "address_components" : [
            {
               "long_name" : "739",
               "short_name" : "739",
               "types" : [ "street_number" ]
            },
            {
               "long_name" : "Caron Avenue",
               "short_name" : "Caron Ave",
               "types" : [ "route" ]
            },
            {
               "long_name" : "City Centre",
               "short_name" : "City Centre",
               "types" : [ "neighborhood", "political" ]
            },
            {
               "long_name" : "Windsor",
               "short_name" : "Windsor",
               "types" : [ "locality", "political" ]
            },
            {
               "long_name" : "Essex County",
               "short_name" : "Essex County",
               "types" : [ "administrative_area_level_2", "political" ]
            },
            {
               "long_name" : "Ontario",
               "short_name" : "ON",
               "types" : [ "administrative_area_level_1", "political" ]
            },
            {
               "long_name" : "Canada",
               "short_name" : "CA",
               "types" : [ "country", "political" ]
            },
            {
               "long_name" : "N9A",
               "short_name" : "N9A",
               "types" : [ "postal_code", "postal_code_prefix" ]
            }
         ],
         "formatted_address" : "739 Caron Ave, Windsor, ON N9A, Canada",
         "geometry" : {
            "bounds" : {
               "northeast" : {
                  "lat" : 42.3099464,
                  "lng" : -83.04356589999999
               },
               "southwest" : {
                  "lat" : 42.3099405,
                  "lng" : -83.04358289999999
               }
            },
            "location" : {
               "lat" : 42.3099464,
               "lng" : -83.04356589999999
            },
            "location_type" : "RANGE_INTERPOLATED",
            "viewport" : {
               "northeast" : {
                  "lat" : 42.31129243029149,
                  "lng" : -83.0422254197085
               },
               "southwest" : {
                  "lat" : 42.3085944697085,
                  "lng" : -83.04492338029151
               }
            }
         },
         "partial_match" : true,
         "place_id" : "EiY3MzkgQ2Fyb24gQXZlLCBXaW5kc29yLCBPTiBOOUEsIENhbmFkYQ",
         "types" : [ "street_address" ]
      }
   ],
   "status" : "OK"
}
