{
   "results" : [
      {
         "address_components" : [
            {
               "long_name" : "596",
               "short_name" : "596",
               "types" : [ "street_number" ]
            },
            {
               "long_name" : "Curry Avenue",
               "short_name" : "Curry Ave",
               "types" : [ "route" ]
            },
            {
               "long_name" : "University",
               "short_name" : "University",
               "types" : [ "neighborhood", "political" ]
            },
            {
               "long_name" : "Windsor",
               "short_name" : "Windsor",
               "types" : [ "locality", "political" ]
            },
            {
               "long_name" : "Essex County",
               "short_name" : "Essex County",
               "types" : [ "administrative_area_level_2", "political" ]
            },
            {
               "long_name" : "Ontario",
               "short_name" : "ON",
               "types" : [ "administrative_area_level_1", "political" ]
            },
            {
               "long_name" : "Canada",
               "short_name" : "CA",
               "types" : [ "country", "political" ]
            },
            {
               "long_name" : "N9B 1Z8",
               "short_name" : "N9B 1Z8",
               "types" : [ "postal_code" ]
            }
         ],
         "formatted_address" : "596 Curry Ave, Windsor, ON N9B 1Z8, Canada",
         "geometry" : {
            "bounds" : {
               "northeast" : {
                  "lat" : 42.30840449999999,
                  "lng" : -83.05393099999999
               },
               "southwest" : {
                  "lat" : 42.3083986,
                  "lng" : -83.0539479
               }
            },
            "location" : {
               "lat" : 42.3083986,
               "lng" : -83.0539479
            },
            "location_type" : "RANGE_INTERPOLATED",
            "viewport" : {
               "northeast" : {
                  "lat" : 42.3097505302915,
                  "lng" : -83.05259046970849
               },
               "southwest" : {
                  "lat" : 42.3070525697085,
                  "lng" : -83.0552884302915
               }
            }
         },
         "partial_match" : true,
         "place_id" : "Eio1OTYgQ3VycnkgQXZlLCBXaW5kc29yLCBPTiBOOUIgMVo4LCBDYW5hZGE",
         "types" : [ "street_address" ]
      }
   ],
   "status" : "OK"
}
