{
   "results" : [
      {
         "address_components" : [
            {
               "long_name" : "1817",
               "short_name" : "1817",
               "types" : [ "street_number" ]
            },
            {
               "long_name" : "Cadillac Street",
               "short_name" : "Cadillac St",
               "types" : [ "route" ]
            },
            {
               "long_name" : "East Windsor",
               "short_name" : "East Windsor",
               "types" : [ "neighborhood", "political" ]
            },
            {
               "long_name" : "Windsor",
               "short_name" : "Windsor",
               "types" : [ "locality", "political" ]
            },
            {
               "long_name" : "Essex County",
               "short_name" : "Essex County",
               "types" : [ "administrative_area_level_2", "political" ]
            },
            {
               "long_name" : "Ontario",
               "short_name" : "ON",
               "types" : [ "administrative_area_level_1", "political" ]
            },
            {
               "long_name" : "Canada",
               "short_name" : "CA",
               "types" : [ "country", "political" ]
            },
            {
               "long_name" : "N8W 3X8",
               "short_name" : "N8W 3X8",
               "types" : [ "postal_code" ]
            }
         ],
         "formatted_address" : "1817 Cadillac St, Windsor, ON N8W 3X8, Canada",
         "geometry" : {
            "location" : {
               "lat" : 42.3057901,
               "lng" : -82.98919909999999
            },
            "location_type" : "ROOFTOP",
            "viewport" : {
               "northeast" : {
                  "lat" : 42.30713908029149,
                  "lng" : -82.98785011970848
               },
               "southwest" : {
                  "lat" : 42.30444111970849,
                  "lng" : -82.99054808029149
               }
            }
         },
         "partial_match" : true,
         "place_id" : "ChIJdxfB7HwrO4gRSmL8NOmG0Nk",
         "types" : [ "street_address" ]
      }
   ],
   "status" : "OK"
}
