{
   "results" : [
      {
         "address_components" : [
            {
               "long_name" : "2217",
               "short_name" : "2217",
               "types" : [ "street_number" ]
            },
            {
               "long_name" : "Woodlawn Avenue",
               "short_name" : "Woodlawn Ave",
               "types" : [ "route" ]
            },
            {
               "long_name" : "South Walkerville",
               "short_name" : "South Walkerville",
               "types" : [ "neighborhood", "political" ]
            },
            {
               "long_name" : "Windsor",
               "short_name" : "Windsor",
               "types" : [ "locality", "political" ]
            },
            {
               "long_name" : "Essex County",
               "short_name" : "Essex County",
               "types" : [ "administrative_area_level_2", "political" ]
            },
            {
               "long_name" : "Ontario",
               "short_name" : "ON",
               "types" : [ "administrative_area_level_1", "political" ]
            },
            {
               "long_name" : "Canada",
               "short_name" : "CA",
               "types" : [ "country", "political" ]
            },
            {
               "long_name" : "N8W 2H4",
               "short_name" : "N8W 2H4",
               "types" : [ "postal_code" ]
            }
         ],
         "formatted_address" : "2217 Woodlawn Ave, Windsor, ON N8W 2H4, Canada",
         "geometry" : {
            "bounds" : {
               "northeast" : {
                  "lat" : 42.2969778,
                  "lng" : -83.00631129999999
               },
               "southwest" : {
                  "lat" : 42.2969718,
                  "lng" : -83.00632829999999
               }
            },
            "location" : {
               "lat" : 42.2969778,
               "lng" : -83.00631129999999
            },
            "location_type" : "RANGE_INTERPOLATED",
            "viewport" : {
               "northeast" : {
                  "lat" : 42.2983237802915,
                  "lng" : -83.00497081970848
               },
               "southwest" : {
                  "lat" : 42.2956258197085,
                  "lng" : -83.0076687802915
               }
            }
         },
         "partial_match" : true,
         "place_id" : "Ei4yMjE3IFdvb2RsYXduIEF2ZSwgV2luZHNvciwgT04gTjhXIDJINCwgQ2FuYWRh",
         "types" : [ "street_address" ]
      }
   ],
   "status" : "OK"
}
