{
   "results" : [
      {
         "address_components" : [
            {
               "long_name" : "1195",
               "short_name" : "1195",
               "types" : [ "street_number" ]
            },
            {
               "long_name" : "Devonshire Road",
               "short_name" : "Devonshire Rd",
               "types" : [ "route" ]
            },
            {
               "long_name" : "Walkerville",
               "short_name" : "Walkerville",
               "types" : [ "neighborhood", "political" ]
            },
            {
               "long_name" : "Windsor",
               "short_name" : "Windsor",
               "types" : [ "locality", "political" ]
            },
            {
               "long_name" : "Essex County",
               "short_name" : "Essex County",
               "types" : [ "administrative_area_level_2", "political" ]
            },
            {
               "long_name" : "Ontario",
               "short_name" : "ON",
               "types" : [ "administrative_area_level_1", "political" ]
            },
            {
               "long_name" : "Canada",
               "short_name" : "CA",
               "types" : [ "country", "political" ]
            },
            {
               "long_name" : "N8Y 2M6",
               "short_name" : "N8Y 2M6",
               "types" : [ "postal_code" ]
            }
         ],
         "formatted_address" : "1195 Devonshire Rd, Windsor, ON N8Y 2M6, Canada",
         "geometry" : {
            "bounds" : {
               "northeast" : {
                  "lat" : 42.3151974,
                  "lng" : -83.00700359999999
               },
               "southwest" : {
                  "lat" : 42.3151914,
                  "lng" : -83.00702059999999
               }
            },
            "location" : {
               "lat" : 42.3151974,
               "lng" : -83.00700359999999
            },
            "location_type" : "RANGE_INTERPOLATED",
            "viewport" : {
               "northeast" : {
                  "lat" : 42.3165433802915,
                  "lng" : -83.00566311970849
               },
               "southwest" : {
                  "lat" : 42.3138454197085,
                  "lng" : -83.00836108029149
               }
            }
         },
         "partial_match" : true,
         "place_id" : "Ei8xMTk1IERldm9uc2hpcmUgUmQsIFdpbmRzb3IsIE9OIE44WSAyTTYsIENhbmFkYQ",
         "types" : [ "street_address" ]
      },
      {
         "address_components" : [
            {
               "long_name" : "1195",
               "short_name" : "1195",
               "types" : [ "street_number" ]
            },
            {
               "long_name" : "Devonshire Court",
               "short_name" : "Devonshire Ct",
               "types" : [ "route" ]
            },
            {
               "long_name" : "Walkerville",
               "short_name" : "Walkerville",
               "types" : [ "neighborhood", "political" ]
            },
            {
               "long_name" : "Windsor",
               "short_name" : "Windsor",
               "types" : [ "locality", "political" ]
            },
            {
               "long_name" : "Essex County",
               "short_name" : "Essex County",
               "types" : [ "administrative_area_level_2", "political" ]
            },
            {
               "long_name" : "Ontario",
               "short_name" : "ON",
               "types" : [ "administrative_area_level_1", "political" ]
            },
            {
               "long_name" : "Canada",
               "short_name" : "CA",
               "types" : [ "country", "political" ]
            },
            {
               "long_name" : "N8Y 1P8",
               "short_name" : "N8Y 1P8",
               "types" : [ "postal_code" ]
            }
         ],
         "formatted_address" : "1195 Devonshire Ct, Windsor, ON N8Y 1P8, Canada",
         "geometry" : {
            "bounds" : {
               "northeast" : {
                  "lat" : 42.3128783,
                  "lng" : -83.00678099999999
               },
               "southwest" : {
                  "lat" : 42.31286559999999,
                  "lng" : -83.0067888
               }
            },
            "location" : {
               "lat" : 42.3128783,
               "lng" : -83.0067888
            },
            "location_type" : "RANGE_INTERPOLATED",
            "viewport" : {
               "northeast" : {
                  "lat" : 42.3142209302915,
                  "lng" : -83.00543591970849
               },
               "southwest" : {
                  "lat" : 42.3115229697085,
                  "lng" : -83.0081338802915
               }
            }
         },
         "partial_match" : true,
         "place_id" : "Ei8xMTk1IERldm9uc2hpcmUgQ3QsIFdpbmRzb3IsIE9OIE44WSAxUDgsIENhbmFkYQ",
         "types" : [ "street_address" ]
      },
      {
         "address_components" : [
            {
               "long_name" : "1195",
               "short_name" : "1195",
               "types" : [ "street_number" ]
            },
            {
               "long_name" : "Devonshire Road",
               "short_name" : "Devonshire Rd",
               "types" : [ "route" ]
            },
            {
               "long_name" : "Grosse Pointe Park",
               "short_name" : "Grosse Pointe Park",
               "types" : [ "locality", "political" ]
            },
            {
               "long_name" : "Wayne County",
               "short_name" : "Wayne County",
               "types" : [ "administrative_area_level_2", "political" ]
            },
            {
               "long_name" : "Michigan",
               "short_name" : "MI",
               "types" : [ "administrative_area_level_1", "political" ]
            },
            {
               "long_name" : "United States",
               "short_name" : "US",
               "types" : [ "country", "political" ]
            },
            {
               "long_name" : "48230",
               "short_name" : "48230",
               "types" : [ "postal_code" ]
            },
            {
               "long_name" : "1418",
               "short_name" : "1418",
               "types" : [ "postal_code_suffix" ]
            }
         ],
         "formatted_address" : "1195 Devonshire Rd, Grosse Pointe Park, MI 48230, USA",
         "geometry" : {
            "bounds" : {
               "northeast" : {
                  "lat" : 42.3847134,
                  "lng" : -82.93109849999999
               },
               "southwest" : {
                  "lat" : 42.3847074,
                  "lng" : -82.93111549999999
               }
            },
            "location" : {
               "lat" : 42.3847134,
               "lng" : -82.93109849999999
            },
            "location_type" : "RANGE_INTERPOLATED",
            "viewport" : {
               "northeast" : {
                  "lat" : 42.3860593802915,
                  "lng" : -82.92975801970847
               },
               "southwest" : {
                  "lat" : 42.3833614197085,
                  "lng" : -82.93245598029149
               }
            }
         },
         "partial_match" : true,
         "place_id" : "EjUxMTk1IERldm9uc2hpcmUgUmQsIEdyb3NzZSBQb2ludGUgUGFyaywgTUkgNDgyMzAsIFVTQQ",
         "types" : [ "street_address" ]
      }
   ],
   "status" : "OK"
}
