{
   "results" : [
      {
         "address_components" : [
            {
               "long_name" : "1582",
               "short_name" : "1582",
               "types" : [ "street_number" ]
            },
            {
               "long_name" : "Benjamin Avenue",
               "short_name" : "Benjamin Ave",
               "types" : [ "route" ]
            },
            {
               "long_name" : "Walkerville",
               "short_name" : "Walkerville",
               "types" : [ "neighborhood", "political" ]
            },
            {
               "long_name" : "Windsor",
               "short_name" : "Windsor",
               "types" : [ "locality", "political" ]
            },
            {
               "long_name" : "Essex County",
               "short_name" : "Essex County",
               "types" : [ "administrative_area_level_2", "political" ]
            },
            {
               "long_name" : "Ontario",
               "short_name" : "ON",
               "types" : [ "administrative_area_level_1", "political" ]
            },
            {
               "long_name" : "Canada",
               "short_name" : "CA",
               "types" : [ "country", "political" ]
            },
            {
               "long_name" : "N8X",
               "short_name" : "N8X",
               "types" : [ "postal_code", "postal_code_prefix" ]
            }
         ],
         "formatted_address" : "1582 Benjamin Ave, Windsor, ON N8X, Canada",
         "geometry" : {
            "bounds" : {
               "northeast" : {
                  "lat" : 42.30382729999999,
                  "lng" : -83.01107809999999
               },
               "southwest" : {
                  "lat" : 42.303823,
                  "lng" : -83.01109599999999
               }
            },
            "location" : {
               "lat" : 42.303823,
               "lng" : -83.01109599999999
            },
            "location_type" : "RANGE_INTERPOLATED",
            "viewport" : {
               "northeast" : {
                  "lat" : 42.3051741302915,
                  "lng" : -83.00973806970849
               },
               "southwest" : {
                  "lat" : 42.3024761697085,
                  "lng" : -83.01243603029151
               }
            }
         },
         "partial_match" : true,
         "place_id" : "EioxNTgyIEJlbmphbWluIEF2ZSwgV2luZHNvciwgT04gTjhYLCBDYW5hZGE",
         "types" : [ "street_address" ]
      }
   ],
   "status" : "OK"
}
