{
   "results" : [
      {
         "address_components" : [
            {
               "long_name" : "1933",
               "short_name" : "1933",
               "types" : [ "street_number" ]
            },
            {
               "long_name" : "Northway Avenue",
               "short_name" : "Northway Ave",
               "types" : [ "route" ]
            },
            {
               "long_name" : "South Cameron",
               "short_name" : "South Cameron",
               "types" : [ "neighborhood", "political" ]
            },
            {
               "long_name" : "Windsor",
               "short_name" : "Windsor",
               "types" : [ "locality", "political" ]
            },
            {
               "long_name" : "Essex County",
               "short_name" : "Essex County",
               "types" : [ "administrative_area_level_2", "political" ]
            },
            {
               "long_name" : "Ontario",
               "short_name" : "ON",
               "types" : [ "administrative_area_level_1", "political" ]
            },
            {
               "long_name" : "Canada",
               "short_name" : "CA",
               "types" : [ "country", "political" ]
            },
            {
               "long_name" : "N9B 0A3",
               "short_name" : "N9B 0A3",
               "types" : [ "postal_code" ]
            }
         ],
         "formatted_address" : "1933 Northway Ave, Windsor, ON N9B 0A3, Canada",
         "geometry" : {
            "location" : {
               "lat" : 42.2809054,
               "lng" : -83.0517904
            },
            "location_type" : "ROOFTOP",
            "viewport" : {
               "northeast" : {
                  "lat" : 42.2822543802915,
                  "lng" : -83.05044141970851
               },
               "southwest" : {
                  "lat" : 42.27955641970851,
                  "lng" : -83.05313938029151
               }
            }
         },
         "partial_match" : true,
         "place_id" : "ChIJWw3OTsctO4gRnVzN3Sl0Wgg",
         "types" : [ "street_address" ]
      }
   ],
   "status" : "OK"
}
