{
   "results" : [
      {
         "address_components" : [
            {
               "long_name" : "814",
               "short_name" : "814",
               "types" : [ "street_number" ]
            },
            {
               "long_name" : "Saint Paul Avenue",
               "short_name" : "St Paul Ave",
               "types" : [ "route" ]
            },
            {
               "long_name" : "Riverside",
               "short_name" : "Riverside",
               "types" : [ "neighborhood", "political" ]
            },
            {
               "long_name" : "Windsor",
               "short_name" : "Windsor",
               "types" : [ "locality", "political" ]
            },
            {
               "long_name" : "Essex County",
               "short_name" : "Essex County",
               "types" : [ "administrative_area_level_2", "political" ]
            },
            {
               "long_name" : "Ontario",
               "short_name" : "ON",
               "types" : [ "administrative_area_level_1", "political" ]
            },
            {
               "long_name" : "Canada",
               "short_name" : "CA",
               "types" : [ "country", "political" ]
            },
            {
               "long_name" : "N8S 1S8",
               "short_name" : "N8S 1S8",
               "types" : [ "postal_code" ]
            }
         ],
         "formatted_address" : "814 St Paul Ave, Windsor, ON N8S 1S8, Canada",
         "geometry" : {
            "bounds" : {
               "northeast" : {
                  "lat" : 42.3330056,
                  "lng" : -82.94504379999999
               },
               "southwest" : {
                  "lat" : 42.3329996,
                  "lng" : -82.9450607
               }
            },
            "location" : {
               "lat" : 42.3329996,
               "lng" : -82.9450607
            },
            "location_type" : "RANGE_INTERPOLATED",
            "viewport" : {
               "northeast" : {
                  "lat" : 42.3343515802915,
                  "lng" : -82.94370326970849
               },
               "southwest" : {
                  "lat" : 42.3316536197085,
                  "lng" : -82.94640123029151
               }
            }
         },
         "partial_match" : true,
         "place_id" : "Eiw4MTQgU3QgUGF1bCBBdmUsIFdpbmRzb3IsIE9OIE44UyAxUzgsIENhbmFkYQ",
         "types" : [ "street_address" ]
      }
   ],
   "status" : "OK"
}
