{
   "results" : [
      {
         "address_components" : [
            {
               "long_name" : "3939",
               "short_name" : "3939",
               "types" : [ "street_number" ]
            },
            {
               "long_name" : "Mount Royal Drive",
               "short_name" : "Mt Royal Dr",
               "types" : [ "route" ]
            },
            {
               "long_name" : "Roseland",
               "short_name" : "Roseland",
               "types" : [ "neighborhood", "political" ]
            },
            {
               "long_name" : "Windsor",
               "short_name" : "Windsor",
               "types" : [ "locality", "political" ]
            },
            {
               "long_name" : "Essex County",
               "short_name" : "Essex County",
               "types" : [ "administrative_area_level_2", "political" ]
            },
            {
               "long_name" : "Ontario",
               "short_name" : "ON",
               "types" : [ "administrative_area_level_1", "political" ]
            },
            {
               "long_name" : "Canada",
               "short_name" : "CA",
               "types" : [ "country", "political" ]
            },
            {
               "long_name" : "N9G 1C3",
               "short_name" : "N9G 1C3",
               "types" : [ "postal_code" ]
            }
         ],
         "formatted_address" : "3939 Mt Royal Dr, Windsor, ON N9G 1C3, Canada",
         "geometry" : {
            "bounds" : {
               "northeast" : {
                  "lat" : 42.2533816,
                  "lng" : -83.01640599999999
               },
               "southwest" : {
                  "lat" : 42.25337589999999,
                  "lng" : -83.0164231
               }
            },
            "location" : {
               "lat" : 42.2533816,
               "lng" : -83.01640599999999
            },
            "location_type" : "RANGE_INTERPOLATED",
            "viewport" : {
               "northeast" : {
                  "lat" : 42.2547277302915,
                  "lng" : -83.0150655697085
               },
               "southwest" : {
                  "lat" : 42.2520297697085,
                  "lng" : -83.0177635302915
               }
            }
         },
         "partial_match" : true,
         "place_id" : "Ei0zOTM5IE10IFJveWFsIERyLCBXaW5kc29yLCBPTiBOOUcgMUMzLCBDYW5hZGE",
         "types" : [ "street_address" ]
      }
   ],
   "status" : "OK"
}
