{
   "results" : [
      {
         "address_components" : [
            {
               "long_name" : "1343",
               "short_name" : "1343",
               "types" : [ "street_number" ]
            },
            {
               "long_name" : "Labadie Road",
               "short_name" : "Labadie Rd",
               "types" : [ "route" ]
            },
            {
               "long_name" : "East Windsor",
               "short_name" : "East Windsor",
               "types" : [ "neighborhood", "political" ]
            },
            {
               "long_name" : "Windsor",
               "short_name" : "Windsor",
               "types" : [ "locality", "political" ]
            },
            {
               "long_name" : "Essex County",
               "short_name" : "Essex County",
               "types" : [ "administrative_area_level_2", "political" ]
            },
            {
               "long_name" : "Ontario",
               "short_name" : "ON",
               "types" : [ "administrative_area_level_1", "political" ]
            },
            {
               "long_name" : "Canada",
               "short_name" : "CA",
               "types" : [ "country", "political" ]
            },
            {
               "long_name" : "N8Y 4G9",
               "short_name" : "N8Y 4G9",
               "types" : [ "postal_code" ]
            }
         ],
         "formatted_address" : "1343 Labadie Rd, Windsor, ON N8Y 4G9, Canada",
         "geometry" : {
            "bounds" : {
               "northeast" : {
                  "lat" : 42.3180757,
                  "lng" : -82.9876371
               },
               "southwest" : {
                  "lat" : 42.3180697,
                  "lng" : -82.98765399999999
               }
            },
            "location" : {
               "lat" : 42.3180757,
               "lng" : -82.9876371
            },
            "location_type" : "RANGE_INTERPOLATED",
            "viewport" : {
               "northeast" : {
                  "lat" : 42.3194216802915,
                  "lng" : -82.98629656970849
               },
               "southwest" : {
                  "lat" : 42.3167237197085,
                  "lng" : -82.98899453029149
               }
            }
         },
         "partial_match" : true,
         "place_id" : "EiwxMzQzIExhYmFkaWUgUmQsIFdpbmRzb3IsIE9OIE44WSA0RzksIENhbmFkYQ",
         "types" : [ "street_address" ]
      }
   ],
   "status" : "OK"
}
