{
   "results" : [
      {
         "address_components" : [
            {
               "long_name" : "Saint Clair Avenue",
               "short_name" : "St Clair Ave",
               "types" : [ "route" ]
            },
            {
               "long_name" : "Windsor",
               "short_name" : "Windsor",
               "types" : [ "locality", "political" ]
            },
            {
               "long_name" : "Essex County",
               "short_name" : "Essex County",
               "types" : [ "administrative_area_level_2", "political" ]
            },
            {
               "long_name" : "Ontario",
               "short_name" : "ON",
               "types" : [ "administrative_area_level_1", "political" ]
            },
            {
               "long_name" : "Canada",
               "short_name" : "CA",
               "types" : [ "country", "political" ]
            },
            {
               "long_name" : "N9H",
               "short_name" : "N9H",
               "types" : [ "postal_code", "postal_code_prefix" ]
            }
         ],
         "formatted_address" : "St Clair Ave, Windsor, ON N9H, Canada",
         "geometry" : {
            "bounds" : {
               "northeast" : {
                  "lat" : 42.2447404,
                  "lng" : -83.02324039999999
               },
               "southwest" : {
                  "lat" : 42.2406331,
                  "lng" : -83.02624399999999
               }
            },
            "location" : {
               "lat" : 42.2429883,
               "lng" : -83.0248447
            },
            "location_type" : "GEOMETRIC_CENTER",
            "viewport" : {
               "northeast" : {
                  "lat" : 42.2447404,
                  "lng" : -83.02324039999999
               },
               "southwest" : {
                  "lat" : 42.2406331,
                  "lng" : -83.02624399999999
               }
            }
         },
         "partial_match" : true,
         "place_id" : "EiVTdCBDbGFpciBBdmUsIFdpbmRzb3IsIE9OIE45SCwgQ2FuYWRh",
         "types" : [ "route" ]
      },
      {
         "address_components" : [
            {
               "long_name" : "Saint Clair College",
               "short_name" : "St Clair College",
               "types" : [ "route" ]
            },
            {
               "long_name" : "Roseland",
               "short_name" : "Roseland",
               "types" : [ "neighborhood", "political" ]
            },
            {
               "long_name" : "Windsor",
               "short_name" : "Windsor",
               "types" : [ "locality", "political" ]
            },
            {
               "long_name" : "Essex County",
               "short_name" : "Essex County",
               "types" : [ "administrative_area_level_2", "political" ]
            },
            {
               "long_name" : "Ontario",
               "short_name" : "ON",
               "types" : [ "administrative_area_level_1", "political" ]
            },
            {
               "long_name" : "Canada",
               "short_name" : "CA",
               "types" : [ "country", "political" ]
            },
            {
               "long_name" : "N9G",
               "short_name" : "N9G",
               "types" : [ "postal_code", "postal_code_prefix" ]
            }
         ],
         "formatted_address" : "St Clair College, Windsor, ON N9G, Canada",
         "geometry" : {
            "bounds" : {
               "northeast" : {
                  "lat" : 42.2496226,
                  "lng" : -83.0149665
               },
               "southwest" : {
                  "lat" : 42.2442248,
                  "lng" : -83.0196342
               }
            },
            "location" : {
               "lat" : 42.2471568,
               "lng" : -83.01673649999999
            },
            "location_type" : "GEOMETRIC_CENTER",
            "viewport" : {
               "northeast" : {
                  "lat" : 42.2496226,
                  "lng" : -83.0149665
               },
               "southwest" : {
                  "lat" : 42.2442248,
                  "lng" : -83.0196342
               }
            }
         },
         "partial_match" : true,
         "place_id" : "ChIJVcOaYJYuO4gRhMf4IgQpk7Q",
         "types" : [ "route" ]
      },
      {
         "address_components" : [
            {
               "long_name" : "St. Clair College - Automotive",
               "short_name" : "St. Clair College - Automotive",
               "types" : [ "premise" ]
            },
            {
               "long_name" : "2000",
               "short_name" : "2000",
               "types" : [ "street_number" ]
            },
            {
               "long_name" : "Talbot Road",
               "short_name" : "Talbot Rd",
               "types" : [ "route" ]
            },
            {
               "long_name" : "Roseland",
               "short_name" : "Roseland",
               "types" : [ "neighborhood", "political" ]
            },
            {
               "long_name" : "Windsor",
               "short_name" : "Windsor",
               "types" : [ "locality", "political" ]
            },
            {
               "long_name" : "Essex County",
               "short_name" : "Essex County",
               "types" : [ "administrative_area_level_2", "political" ]
            },
            {
               "long_name" : "Ontario",
               "short_name" : "ON",
               "types" : [ "administrative_area_level_1", "political" ]
            },
            {
               "long_name" : "Canada",
               "short_name" : "CA",
               "types" : [ "country", "political" ]
            },
            {
               "long_name" : "N9G 3C3",
               "short_name" : "N9G 3C3",
               "types" : [ "postal_code" ]
            }
         ],
         "formatted_address" : "St. Clair College - Automotive, 2000 Talbot Rd, Windsor, ON N9G 3C3, Canada",
         "geometry" : {
            "bounds" : {
               "northeast" : {
                  "lat" : 42.2474032,
                  "lng" : -83.01932459999999
               },
               "southwest" : {
                  "lat" : 42.2469241,
                  "lng" : -83.02004359999999
               }
            },
            "location" : {
               "lat" : 42.2471218,
               "lng" : -83.01977269999999
            },
            "location_type" : "ROOFTOP",
            "viewport" : {
               "northeast" : {
                  "lat" : 42.2485126302915,
                  "lng" : -83.0183351197085
               },
               "southwest" : {
                  "lat" : 42.2458146697085,
                  "lng" : -83.0210330802915
               }
            }
         },
         "partial_match" : true,
         "place_id" : "ChIJu2J9zpYuO4gRn0vLV-b8L7k",
         "types" : [ "premise" ]
      }
   ],
   "status" : "OK"
}
