{
   "results" : [
      {
         "address_components" : [
            {
               "long_name" : "952",
               "short_name" : "952",
               "types" : [ "street_number" ]
            },
            {
               "long_name" : "Banwell Road",
               "short_name" : "Banwell Rd",
               "types" : [ "route" ]
            },
            {
               "long_name" : "East Riverside",
               "short_name" : "East Riverside",
               "types" : [ "neighborhood", "political" ]
            },
            {
               "long_name" : "Windsor",
               "short_name" : "Windsor",
               "types" : [ "locality", "political" ]
            },
            {
               "long_name" : "Essex County",
               "short_name" : "Essex County",
               "types" : [ "administrative_area_level_2", "political" ]
            },
            {
               "long_name" : "Ontario",
               "short_name" : "ON",
               "types" : [ "administrative_area_level_1", "political" ]
            },
            {
               "long_name" : "Canada",
               "short_name" : "CA",
               "types" : [ "country", "political" ]
            },
            {
               "long_name" : "N8P 1J2",
               "short_name" : "N8P 1J2",
               "types" : [ "postal_code" ]
            }
         ],
         "formatted_address" : "952 Banwell Rd, Windsor, ON N8P 1J2, Canada",
         "geometry" : {
            "location" : {
               "lat" : 42.3302142,
               "lng" : -82.9044748
            },
            "location_type" : "ROOFTOP",
            "viewport" : {
               "northeast" : {
                  "lat" : 42.3315631802915,
                  "lng" : -82.90312581970849
               },
               "southwest" : {
                  "lat" : 42.3288652197085,
                  "lng" : -82.9058237802915
               }
            }
         },
         "partial_match" : true,
         "place_id" : "ChIJH6AyHlXVOogRV2A3EmQrprU",
         "types" : [ "street_address" ]
      }
   ],
   "status" : "OK"
}
