{
   "results" : [
      {
         "address_components" : [
            {
               "long_name" : "2161",
               "short_name" : "2161",
               "types" : [ "street_number" ]
            },
            {
               "long_name" : "Kildare Road",
               "short_name" : "Kildare Rd",
               "types" : [ "route" ]
            },
            {
               "long_name" : "South Walkerville",
               "short_name" : "South Walkerville",
               "types" : [ "neighborhood", "political" ]
            },
            {
               "long_name" : "Windsor",
               "short_name" : "Windsor",
               "types" : [ "locality", "political" ]
            },
            {
               "long_name" : "Essex County",
               "short_name" : "Essex County",
               "types" : [ "administrative_area_level_2", "political" ]
            },
            {
               "long_name" : "Ontario",
               "short_name" : "ON",
               "types" : [ "administrative_area_level_1", "political" ]
            },
            {
               "long_name" : "Canada",
               "short_name" : "CA",
               "types" : [ "country", "political" ]
            },
            {
               "long_name" : "N8W 2W9",
               "short_name" : "N8W 2W9",
               "types" : [ "postal_code" ]
            }
         ],
         "formatted_address" : "2161 Kildare Rd, Windsor, ON N8W 2W9, Canada",
         "geometry" : {
            "bounds" : {
               "northeast" : {
                  "lat" : 42.3006878,
                  "lng" : -82.99907999999999
               },
               "southwest" : {
                  "lat" : 42.3006818,
                  "lng" : -82.99909699999999
               }
            },
            "location" : {
               "lat" : 42.3006878,
               "lng" : -82.99907999999999
            },
            "location_type" : "RANGE_INTERPOLATED",
            "viewport" : {
               "northeast" : {
                  "lat" : 42.3020337802915,
                  "lng" : -82.99773951970849
               },
               "southwest" : {
                  "lat" : 42.2993358197085,
                  "lng" : -83.00043748029151
               }
            }
         },
         "partial_match" : true,
         "place_id" : "EiwyMTYxIEtpbGRhcmUgUmQsIFdpbmRzb3IsIE9OIE44VyAyVzksIENhbmFkYQ",
         "types" : [ "street_address" ]
      }
   ],
   "status" : "OK"
}
