{
   "results" : [
      {
         "address_components" : [
            {
               "long_name" : "2128",
               "short_name" : "2128",
               "types" : [ "street_number" ]
            },
            {
               "long_name" : "Dominion Boulevard",
               "short_name" : "Dominion Blvd",
               "types" : [ "route" ]
            },
            {
               "long_name" : "South Cameron",
               "short_name" : "South Cameron",
               "types" : [ "neighborhood", "political" ]
            },
            {
               "long_name" : "Windsor",
               "short_name" : "Windsor",
               "types" : [ "locality", "political" ]
            },
            {
               "long_name" : "Essex County",
               "short_name" : "Essex County",
               "types" : [ "administrative_area_level_2", "political" ]
            },
            {
               "long_name" : "Ontario",
               "short_name" : "ON",
               "types" : [ "administrative_area_level_1", "political" ]
            },
            {
               "long_name" : "Canada",
               "short_name" : "CA",
               "types" : [ "country", "political" ]
            },
            {
               "long_name" : "N9B 3H9",
               "short_name" : "N9B 3H9",
               "types" : [ "postal_code" ]
            }
         ],
         "formatted_address" : "2128 Dominion Blvd, Windsor, ON N9B 3H9, Canada",
         "geometry" : {
            "bounds" : {
               "northeast" : {
                  "lat" : 42.2837323,
                  "lng" : -83.03568249999999
               },
               "southwest" : {
                  "lat" : 42.2837265,
                  "lng" : -83.0356996
               }
            },
            "location" : {
               "lat" : 42.2837265,
               "lng" : -83.0356996
            },
            "location_type" : "RANGE_INTERPOLATED",
            "viewport" : {
               "northeast" : {
                  "lat" : 42.28507838029149,
                  "lng" : -83.03434206970849
               },
               "southwest" : {
                  "lat" : 42.2823804197085,
                  "lng" : -83.03704003029151
               }
            }
         },
         "partial_match" : true,
         "place_id" : "Ei8yMTI4IERvbWluaW9uIEJsdmQsIFdpbmRzb3IsIE9OIE45QiAzSDksIENhbmFkYQ",
         "types" : [ "street_address" ]
      }
   ],
   "status" : "OK"
}
